baoshare-0.5.4.dist-info/DESCRIPTION.rst
baoshare-0.5.4.dist-info/METADATA
baoshare-0.5.4.dist-info/RECORD
baoshare-0.5.4.dist-info/WHEEL
baoshare-0.5.4.dist-info/metadata.json
baoshare-0.5.4.dist-info/top_level.txt
baostock/__init__.py
baostock/common/__init__.py
baostock/common/contants.py
baostock/common/context.py
baostock/data/__init__.py
baostock/data/messageheader.py
baostock/data/msg.py
baostock/data/resultset.py
baostock/login/__init__.py
baostock/login/loginout.py
baostock/security/__init__.py
baostock/security/history.py
baostock/util/__init__.py
baostock/util/socketutil.py
baostock/util/stringutil.py
demo/__init__.py
demo/helloWorld.py
